[
  [
    {
      "action": "verify",
      "selector": "primary navigation bar",
      "value": "",
      "expected": {
        "background-color": "#F0F0F0",
        "height": "60px"
      }
    },
    {
      "action": "verify",
      "selector": "'Products' link",
      "value": "",
      "expected": {
        "text-content": "Products",
        "font-size": "16px",
        "color": "#333333"
      }
    },
    {
      "action": "verify",
      "selector": "'Products' link",
      "value": "",
      "expected": {
        "focused": true,
        "outline-width": "2px",
        "outline-style": "solid",
        "outline-color": "#007bff"
      }
    },
    {
      "action": "verify",
      "selector": "'About Us' link",
      "value": "",
      "expected": {
        "aria-label": "About company information"
      }
    }
  ],
  [
    {
      "action": "goto",
      "selector": "",
      "value": "https://demo.example.com/item/P001",
      "expected": {
        "url": "https://demo.example.com/item/P001"
      }
    },
    {
      "action": "verify",
      "selector": "main product image",
      "value": "",
      "expected": {
        "src": "product_P001_main.jpg",
        "rendered-width": 600,
        "rendered-height": 400,
        "alt-text": "Stylish Leather Jacket",
        "load-time": 150,
        "watermark": false
      }
    }
  ],
  [
    {
      "action": "verify",
      "selector": "'Add to Cart' button",
      "value": "",
      "expected": {
        "visibility": "visible",
        "enabled": true,
        "background-color": "#28A745",
        "color": "#FFFFFF",
        "border-radius": "8px"
      }
    },
    {
      "action": "verify",
      "selector": "'Add to Cart' button",
      "value": "",
      "expected": {
        "hovered": true,
        "background-color": "#218838",
        "transition-duration": 200,
        "padding-top": "12px",
        "padding-right": "24px",
        "padding-bottom": "12px",
        "padding-left": "24px"
      }
    }
  ],
  [
    {
      "action": "verify",
      "selector": "search input field",
      "value": "",
      "expected": {
        "placeholder": "Search for products...",
        "width": "250px",
        "height": "40px",
        "border-width": "1px",
        "border-style": "solid",
        "border-color": "#CCCCCC"
      }
    },
    {
      "action": "verify",
      "selector": "search input field",
      "value": "",
      "expected": {
        "focused": true,
        "border-color": "#007BFF",
        "margin-left": "10px"
      }
    }
  ],
  [
    {
      "action": "click",
      "selector": "'user profile' link",
      "value": "",
      "expected": {}
    },
    {
      "action": "verify",
      "selector": "user avatar image",
      "value": "",
      "expected": {
        "src": "user_profile_123.png",
        "border-radius": "50%",
        "width": "80px",
        "height": "80px",
        "natural-width": 160,
        "natural-height": 160,
        "load-time": 100,
        "text-align": "center"
      }
    }
  ],
  [
    {
      "action": "play",
      "selector": "video player",
      "value": "https://example.com/video/intro.mp4",
      "expected": {}
    },
    {
      "action": "verify",
      "selector": "'Play/Pause' button",
      "value": "",
      "expected": {
        "visibility": "visible",
        "icon-color": "#FFFFFF",
        "text-content": [
          "Play",
          "Pause"
        ]
      }
    },
    {
      "action": "verify",
      "selector": "volume icon",
      "value": "",
      "expected": {
        "muted": false,
        "fullscreen": false
      }
    }
  ],
  [
    {
      "action": "submit",
      "selector": "form",
      "value": "invalid data",
      "expected": {}
    },
    {
      "action": "verify",
      "selector": "error message 'Invalid email format'",
      "value": "",
      "expected": {
        "text-content": "Invalid email format",
        "position": "below email input field",
        "font-size": "14px",
        "color": "#DC3545",
        "margin-top": "5px",
        "background-color": "#FFF3F3"
      }
    }
  ],
  [
    {
      "action": "verify",
      "selector": "pagination component",
      "value": "",
      "expected": {
        "page-count": 5
      }
    },
    {
      "action": "verify",
      "selector": "'Next' button",
      "value": "",
      "expected": {
        "enabled": true,
        "color": "#007BFF"
      }
    },
    {
      "action": "verify",
      "selector": "active page number '3'",
      "value": "",
      "expected": {
        "text-content": "3",
        "background-color": "#007BFF",
        "color": "#FFFFFF"
      }
    }
  ],
  [
    {
      "action": "click",
      "selector": "'Open Modal'",
      "value": "",
      "expected": {}
    },
    {
      "action": "verify",
      "selector": "modal dialog",
      "value": "",
      "expected": {
        "visibility": "visible",
        "x": "50%",
        "y": "50%",
        "width": "500px",
        "height": "300px",
        "background-color": "#FFFFFF"
      }
    },
    {
      "action": "verify",
      "selector": "overlay background",
      "value": "",
      "expected": {
        "opacity": 0.7,
        "background-color": "#000000"
      }
    }
  ],
  [
    {
      "action": "verify",
      "selector": "quantity input field for 'Item X'",
      "value": "",
      "expected": {
        "value": "1",
        "width": "60px",
        "height": "32px",
        "border": "1px solid #CED4DA"
      }
    },
    {
      "action": "verify",
      "selector": "'Increment' button",
      "value": "",
      "expected": {
        "enabled": true,
        "padding-top": "4px",
        "padding-right": "4px",
        "padding-bottom": "4px",
        "padding-left": "4px",
        "border-radius": "4px"
      }
    }
  ],
  [
    {
      "action": "verify",
      "selector": "'Privacy Policy' link in the footer",
      "value": "",
      "expected": {
        "font-size": "13px",
        "color": "#6C757D",
        "href": "https://example.com/privacy",
        "text-decoration-line": "none",
        "padding-right": "15px"
      }
    }
  ],
  [
    {
      "action": "click",
      "selector": "second thumbnail",
      "value": "",
      "expected": {}
    },
    {
      "action": "verify",
      "selector": "second thumbnail",
      "value": "",
      "expected": {
        "active": true,
        "border": "2px solid #007BFF",
        "opacity": 1.0
      }
    },
    {
      "action": "verify",
      "selector": "main image",
      "value": "",
      "expected": {
        "src": "gallery_image_2.jpg"
      }
    }
  ],
  [
    {
      "action": "resize",
      "selector": "viewport",
      "value": "",
      "expected": {
        "viewport-width": "767px"
      }
    },
    {
      "action": "verify",
      "selector": "'Hamburger' menu icon",
      "value": "",
      "expected": {
        "visibility": "visible",
        "x": "20px",
        "y": "15px",
        "width": "30px",
        "height": "25px"
      }
    },
    {
      "action": "verify",
      "selector": "main navigation links",
      "value": "",
      "expected": {
        "visibility": "hidden",
        "text-align": "right"
      }
    }
  ],
  [
    {
      "action": "click",
      "selector": "date input field",
      "value": "",
      "expected": {}
    },
    {
      "action": "verify",
      "selector": "date picker calendar",
      "value": "",
      "expected": {
        "visibility": "visible",
        "y-offset": "36px",
        "background-color": "#FFFFFF"
      }
    },
    {
      "action": "verify",
      "selector": "selected date '2023-10-26'",
      "value": "",
      "expected": {
        "background-color": "#007BFF"
      }
    }
  ],
  [
    {
      "action": "scroll",
      "selector": "page",
      "value": "",
      "expected": {
        "scroll-y": "800px"
      }
    },
    {
      "action": "verify",
      "selector": "'Scroll to Top' button",
      "value": "",
      "expected": {
        "visibility": "visible",
        "bottom": "20px",
        "right": "20px",
        "background-color": "rgba(0,0,0,0.5)"
      }
    },
    {
      "action": "verify",
      "selector": "'Scroll to Top' button",
      "value": "",
      "expected": {
        "scroll-y": "0px",
        "timeout": 500
      }
    }
  ],
  [
    {
      "action": "verify",
      "selector": "product description text block",
      "value": "",
      "expected": {
        "font-family": "Arial",
        "font-size": "15px",
        "font-weight": 400,
        "color": "#333333",
        "margin-top": "20px",
        "padding-bottom": "10px"
      }
    }
  ],
  [
    {
      "action": "verify",
      "selector": "'Download Report' button",
      "value": "",
      "expected": {
        "enabled": true,
        "text-content": "Download Report",
        "background-color": "#17A2B8",
        "border-radius": "5px"
      }
    },
    {
      "action": "verify",
      "selector": "'Download Report' button",
      "value": "",
      "expected": {
        "text-content": "Downloading...",
        "enabled": false
      }
    }
  ],
  [
    {
      "action": "verify",
      "selector": "table rows",
      "value": "",
      "expected": {
        "height": "40px",
        "background-color": "#ffffff"
      }
    },
    {
      "action": "verify",
      "selector": "a table row",
      "value": "",
      "expected": {
        "hovered": true,
        "background-color": "#f8f9fa",
        "transition-duration": "150ms"
      }
    },
    {
      "action": "verify",
      "selector": "'Status' column text",
      "value": "",
      "expected": {
        "text-align": "center"
      }
    }
  ],
  [
    {
      "action": "click",
      "selector": "'Fullscreen' button on the video player",
      "value": "",
      "expected": {}
    },
    {
      "action": "verify",
      "selector": "video player",
      "value": "",
      "expected": {
        "fullscreen": true,
        "width": "100vw",
        "height": "100vh"
      }
    },
    {
      "action": "verify",
      "selector": "'Fullscreen' button",
      "value": "",
      "expected": {
        "aria-label": "Exit Fullscreen"
      }
    }
  ],
  [
    {
      "action": "click",
      "selector": "'Toggle Menu' button",
      "value": "",
      "expected": {}
    },
    {
      "action": "verify",
      "selector": "sidebar menu",
      "value": "",
      "expected": {
        "visibility": "visible",
        "x": "0px",
        "width": "250px",
        "background-color": "#343a40",
        "opacity": 1.0,
        "transition-duration": "300ms",
        "movement": "x from -250px to 0px",
        "animation": "opacity from 0 to 1.0"
      }
    }
  ]
]